Metadata-Version: 1.0
Name: allmath
Version: 0.0
Summary: Your go to library for all Math operations
Home-page: UNKNOWN
Author: UNKNOWN
Author-email: churiwalanaman@gmail.com
License: UNKNOWN
Platform: UNKNOWN
